langchain_amvera/__init__.py
langchain_amvera/amvera.py
langchain_amvera-0.3.1.dist-info/licenses/LICENSE
langchain_amvera-0.3.1.dist-info/METADATA
langchain_amvera-0.3.1.dist-info/WHEEL
langchain_amvera-0.3.1.dist-info/top_level.txt
langchain_amvera-0.3.1.dist-info/RECORD
