Metadata-Version: 2.4
Name: langchain-amvera
Version: 0.3.1
Summary: LangChain интеграция для Amvera LLM API с поддержкой LLaMA и GPT моделей
Author-email: Alexey Yakovenko <mr.mnogo@gmail.com>
License: MIT
Project-URL: Homepage, https://github.com/Yakvenalex/langchain-amvera
Project-URL: Repository, https://github.com/Yakvenalex/langchain-amvera
Project-URL: Documentation, https://github.com/Yakvenalex/langchain-amvera
Project-URL: Bug Reports, https://github.com/Yakvenalex/langchain-amvera/issues
Keywords: langchain,amvera,llm,ai,chatbot,yakvenalex
Classifier: Development Status :: 4 - Beta
Classifier: Intended Audience :: Developers
Classifier: License :: OSI Approved :: MIT License
Classifier: Operating System :: OS Independent
Classifier: Programming Language :: Python :: 3
Classifier: Programming Language :: Python :: 3.8
Classifier: Programming Language :: Python :: 3.9
Classifier: Programming Language :: Python :: 3.10
Classifier: Programming Language :: Python :: 3.11
Classifier: Programming Language :: Python :: 3.12
Classifier: Topic :: Software Development :: Libraries :: Python Modules
Classifier: Topic :: Scientific/Engineering :: Artificial Intelligence
Requires-Python: >=3.8
License-File: LICENSE
Requires-Dist: langchain-core>=0.1.0
Requires-Dist: langchain>=0.1.0
Requires-Dist: httpx>=0.24.0
Requires-Dist: pydantic>=2.0.0
Requires-Dist: python-dotenv>=0.19.0
Provides-Extra: dev
Requires-Dist: pytest>=7.0.0; extra == "dev"
Requires-Dist: pytest-asyncio>=0.21.0; extra == "dev"
Requires-Dist: black>=23.0.0; extra == "dev"
Requires-Dist: ruff>=0.1.0; extra == "dev"
Requires-Dist: mypy>=1.0.0; extra == "dev"
Provides-Extra: test
Requires-Dist: pytest>=7.0.0; extra == "test"
Requires-Dist: pytest-asyncio>=0.21.0; extra == "test"
Requires-Dist: pytest-mock>=3.10.0; extra == "test"
Requires-Dist: responses>=0.23.0; extra == "test"
Dynamic: license-file
